{
    "brand": [{
        "Shoei": [{
            "Product": [{
                "SHOEI X-Spirit 3 Black Concept": {
                    "id": "370120338632",
                    "Information": "SHOEI รุ่น X-Spirit 3 Black Concept หมวกกันน็อคที่ถูกพัฒนาขึ้นโดยผู้ขับขี่ MotoGP โครงสร้าง AIM+ (Advanced Integrated Matrix) สายรัดคางแบบ Double D-Ring",
                    "price": 26500,
                    "img": "https://www.lovebigbike.com/wp-content/uploads/2019/07/SHOEI_X_SPIRIT_III_MARQUEZ_BLACK_CONCEPT_TC_1_1.jpg"
                },
                "SHOEI X-Spirit 3 Marquez 4 TC-6": {
                    "id": "370120590221",
                    "information": "หมวกกันน็อค SHOEI X-Spirit 3 Marquez 4 โครงสร้าง AIM (Advanced Integrated Matrix) แข็งแรงแต่น้ำหนักเบา มาตรฐานระดับโลกส่งตรงจากญี่ปุ่น",
                    "price": 26500,
                    "img": "https://www.lovebigbike.com/wp-content/uploads/2019/08/SHOEI_X_Spirit_3_Marquez_4_1.jpg"
                },
                "SHOEI X-Spirit 3 Marquez 4 TC-1": {
                    "id": "370120353636",
                    "information": "หมวกกันน็อค SHOEI X-Spirit 3 Marquez 4 TC-1 โครงสร้าง AIM (Advanced Integrated Matrix) แข็งแรงแต่น้ำหนักเบา มาตรฐานระดับโลกส่งตรงจากญี่ปุ่น",
                    "price": 26500,
                    "img": "https://www.lovebigbike.com/wp-content/uploads/2019/08/SHOEI_X_Spirit_3_Marquez_4_4.jpg"
                },
                "SHOEI X-SPIRIT3 – BRINK TC-1": {
                    "id": "370120863163",
                    "information": "หมวกกัันน็อคหลากสีสัน สีก็โดน ราคาก็ดี มาพร้อมแบบให้เลือกหลากหลาย สั่งเลยย!",
                    "price": 26500,
                    "img": "https://www.lovebigbike.com/wp-content/uploads/2018/02/SHOEI_X_SPIRIT3_BRINK_1.jpg"
                },
                "SHOEI X-SPIRIT3 – MARQUEZ MOTEGI": {
                    "id": "370120863259",
                    "information": "หมวกกันน็อค Limited Edition รุ่นใหม่ล่าสุดจาก Shoei นำเข้าจากประเทศญี่ปุ่น โดดเด่นด้วยลวดลายนักแข่งชื่อดังอย่าง Mark MARQUEZ ลายนี้ผลิตครั้งเดียว ห้ามพลาด",
                    "price": 26500,
                    "img": "https://www.lovebigbike.com/wp-content/uploads/2017/11/MARQUEZ-MOTEGI_1.jpg"
                },
                "SHOEI X-Spirit 3 Brink TC5": {
                    "id": "370120863182",
                    "information": "หมวกกันน็อค SHOEI รุ่น X-Spirit 3 Brink หมวกกันน็อคที่ถูกพัฒนาขึ้นโดยผู้ขับขี่ MotoGP โครงสร้าง AIM+ (Advanced Integrated Matrix) สายรัดคางแบบ Double D-Ring",
                    "price": 26500,
                    "img": "https://www.lovebigbike.com/wp-content/uploads/2019/07/2_Shoei-Xspirit3-Blink-TC5.jpg"
                },
                "SHOEI X-Spirit 3 Marquez Motegi 3 TC-2": {
                    "id": "370120863273",
                    "information": "",
                    "price": 26500,
                    "img": "https://www.lovebigbike.com/wp-content/uploads/2019/08/SHOEI_X_Spirit_3_Marquez_Motegi_3_TC_2_1.jpg"
                },
                "SHOEI Z7 – INDY MARQUEZ TC-2": {
                    "id": "370120863159",
                    "information": "หมวกกันน็อครุ่นใหม่ล่าสุดจาก Shoei นำเข้าจากประเทศญี่ปุ่น โดดเด่นด้วยลวดลายนักแข่งชื่อดังอย่าง Mark MARQUEZ พิเศษสุดๆ ไปเลย",
                    "price": 18500,
                    "img": "https://www.lovebigbike.com/wp-content/uploads/2017/10/Indy-Marquez-TC-2_1.jpg"
                },
                "SHOEI X-SPIRIT3": {
                    "id": "370120338636",
                    "information": "หมวกกันน็อคเต็มใบ ออกแบบอย่างดีเพื่อการแข่งขันโดยเฉพาะ เพิ่มรูระบายอากาศและช่องหายใจรอบปาก",
                    "price": 24500,
                    "img": "https://www.lovebigbike.com/wp-content/uploads/2017/07/X-SPIRIT3-Basic-1.jpg"
                },
                "SHOEI GT-Air Expanse": {
                    "id": "370120914026",
                    "information": "SHOEI GT-Air Expanse แว่นกันแดดในตัว (Drop-down Internal Sun Visor) เหมาะกับการสวมใส่เพื่อออกทริปทัวร์ริ่งและผจญภัย มีตำแหน่งของช่องระบายอากาศที่ดีกว่า",
                    "price": 17100,
                    "img": "https://www.lovebigbike.com/wp-content/uploads/2019/06/SHOEI_GT_AirExpanse_1.jpg"
                }
            }]
        }]
    }]
}